cryptography318/__init__.py
cryptography318/dlp/__init__.py
cryptography318/dlp/dlp.py
cryptography318/dlp/dlp.pyi
cryptography318/factor/__init__.py
cryptography318/factor/elliptic.py
cryptography318/factor/elliptic.pyi
cryptography318/factor/factor.py
cryptography318/factor/factor.pyi
cryptography318/factor/qs.py
cryptography318/factor/qs.pyi
cryptography318/linalg/__init__.py
cryptography318/linalg/linalg.py
cryptography318/linalg/linalg.pyi
cryptography318/prime/__init__.py
cryptography318/prime/bailliepsw_helper.py
cryptography318/prime/bailliepsw_helper.pyi
cryptography318/prime/prime.py
cryptography318/prime/prime.pyi
cryptography318/prime/primesieve.py
cryptography318/prime/primesieve.pyi
cryptography318/utils/__init__.py
cryptography318/utils/dlp.py
cryptography318/utils/misc.py
cryptography318/utils/root.py
cryptography318/utils/siqs.py
cryptography318-1.0.0.dist-info/METADATA
cryptography318-1.0.0.dist-info/WHEEL
cryptography318-1.0.0.dist-info/top_level.txt
cryptography318-1.0.0.dist-info/RECORD
