Metadata-Version: 2.1
Name: cryptography318
Version: 1.0.0
Summary: A set of functions useful in mathematical cryptography
Home-page: https://github.com/aarpyy/Cryptography
Author: Andrew Carpenter
Author-email: andrewcarp00@gmail.com
Project-URL: Source, https://github.com/aarpyy/Cryptography
Classifier: Development Status :: 2 - Pre-Alpha
Classifier: Intended Audience :: Education
Classifier: License :: OSI Approved :: MIT License
Classifier: Operating System :: OS Independent
Classifier: Topic :: Scientific/Engineering
Classifier: Topic :: Scientific/Engineering :: Mathematics
Classifier: Programming Language :: Python :: 3.10
Classifier: Programming Language :: Python :: 3.11
Requires-Python: >=3.10
Requires-Dist: numpy ==1.26.2
